{
  "active": {
    "autogluon": "autogluon-001.py",
    "legacy": "legacy-001.py"
  },
  "versions": {
    "autogluon": [
      {
        "file": "autogluon-001.py",
        "node_id": "551653a2b3ff49c9b978f7a90f51e05b",
        "created_at": "2026-05-18T07:56:36",
        "buggy": false,
        "score": 0.9513759696979146
      }
    ],
    "legacy": [
      {
        "file": "legacy-001.py",
        "buggy": false,
        "node_id": "f5e0c02f0b0a4aa485676bca1799ac55",
        "score": null,
        "created_at": "2026-05-23T23:23:35"
      }
    ]
  }
}
